fml/__init__.py
fml/cli.py
fml/continuous_parser.py
fml/parser.py
fml/renderer.py
fml/server.py
fml_md-0.1.1.dist-info/licenses/LICENSE
fml_md-0.1.1.dist-info/METADATA
fml_md-0.1.1.dist-info/WHEEL
fml_md-0.1.1.dist-info/entry_points.txt
fml_md-0.1.1.dist-info/top_level.txt
fml_md-0.1.1.dist-info/RECORD
