Metadata-Version: 2.4
Name: fml-md
Version: 0.1.1
Summary: Fibonacci Markup Language - where indentation follows the Fibonacci sequence
Home-page: https://github.com/OwPor/fml-md
Author: OwPor
Author-email: concepcionrayvincent@gmail.com
Keywords: fibonacci,markup,language,indentation
Classifier: Programming Language :: Python :: 3
Classifier: License :: OSI Approved :: MIT License
Classifier: Operating System :: OS Independent
Classifier: Development Status :: 4 - Beta
Classifier: Intended Audience :: Developers
Classifier: Topic :: Software Development :: Libraries :: Python Modules
Classifier: Topic :: Text Processing :: Markup
Requires-Python: >=3.6
License-File: LICENSE
Requires-Dist: click>=8.0.0
Requires-Dist: markdown>=3.3.0
Requires-Dist: pygments>=2.7.0
Dynamic: author
Dynamic: author-email
Dynamic: classifier
Dynamic: description
Dynamic: description-content-type
Dynamic: home-page
Dynamic: keywords
Dynamic: license-file
Dynamic: requires-dist
Dynamic: requires-python
Dynamic: summary
